{"meta":{"id":"canada","displayText":"Canada","version":1,"tableStyle":"alphabetical","shapeCutoff":0,"missingCount":3,"supports":{"deserts":false,"endonyms":false,"marine":true,"mountains":false,"ranges":false,"letters":false}},"extraRegions":[],"elements":[{"iso2":"YT","iso3":"YT","name":"Yukon","letter":"Y","audio":"YUKONTERRITORY.mp3","aliases":[{"val":"YUKON","mode":"s"}],"type":"land","quizRegion":"North Americas","quizSubRegion":"","region":"Americas","intermediateRegion":"","subRegion":"Northern America","capital":{"name":"Whitehorse","aliases":[{"val":"WHITEHORSE","mode":"s"}],"speech":"Whitehorse Yukon","lat":60.724167,"lon":-135.056111,"state":"YT","timezone":"America/Whitehorse","ipa":""},"lat":63,"lon":-135,"dotX":0,"dotY":0,"additionalCities":[],"ipa":"","nativeName":"","areaSqKm":482443,"areaSqMi":186272},{"iso2":"SK","iso3":"SK","name":"Saskatchewan","letter":"S","audio":"SASKATCHEWAN.mp3","aliases":[{"val":"SASKATCHEWAN","mode":"s"}],"type":"land","quizRegion":"North Americas","quizSubRegion":"","region":"Americas","intermediateRegion":"","subRegion":"Northern America","capital":{"name":"Regina","aliases":[{"val":"REGINA","mode":"s"}],"speech":"Regina Saskatchewan","lat":50.43,"lon":-104.62,"timezone":"America/Regina","state":"SK","ipa":""},"lat":54,"lon":-106,"dotX":0,"dotY":0,"additionalCities":[],"ipa":"","nativeName":"","areaSqKm":591670,"areaSqMi":228450},{"iso2":"QC","iso3":"QC","name":"Quebec","letter":"Q","audio":"QUEBEC.mp3","aliases":[{"val":"QUEBEC","mode":"s"}],"type":"land","quizRegion":"North Americas","quizSubRegion":"","region":"Americas","intermediateRegion":"","subRegion":"Northern America","capital":{"name":"Quebec City","aliases":[{"val":"QUEBECCITY","mode":"s"}],"speech":"Quebec City Quebec","lat":46.813889,"lon":-71.208056,"timezone":"America/Toronto","state":"QC","ipa":""},"lat":52,"lon":-72,"dotX":0,"dotY":0,"additionalCities":[],"ipa":"","nativeName":"","areaSqKm":1542057,"areaSqMi":595392},{"iso2":"PE","iso3":"PE","name":"Prince Edward Island","letter":"P","audio":"PRINCEEDWARDISLAND.mp3","aliases":[{"val":"PRINCEEDWARD","mode":"s"}],"type":"land","quizRegion":"North Americas","quizSubRegion":"","region":"Americas","intermediateRegion":"","subRegion":"Northern America","capital":{"name":"Charlottetown","aliases":[{"val":"CHARLOTTETOWN","mode":"s"}],"speech":"Charlottetown Prince Edward Island","lat":46.235278,"lon":-63.126667,"timezone":"America/Halifax","state":"PE","ipa":""},"lat":52,"lon":-72,"dotX":0,"dotY":0,"additionalCities":[],"ipa":"","nativeName":"","areaSqKm":5660,"areaSqMi":2185.3},{"iso2":"ON","iso3":"ON","name":"Ontario","letter":"O","audio":"ONTARIO.mp3","aliases":[{"val":"ONTARIO","mode":"s"}],"type":"land","quizRegion":"North Americas","quizSubRegion":"","region":"Americas","intermediateRegion":"","subRegion":"Northern America","capital":{"name":"Toronto","aliases":[{"val":"TORONTO","mode":"s"}],"speech":"Toronto Ontario","lat":43.6667,"lon":-79.3833,"timezone":"America/Toronto","state":"ON","ipa":""},"lat":49.25,"lon":-84.5,"dotX":0,"dotY":0,"additionalCities":[],"ipa":"","nativeName":"","areaSqKm":892412,"areaSqMi":344562},{"iso2":"NU","iso3":"NU","name":"Nunavut","letter":"N","audio":"NUNAVUT.mp3","aliases":[{"val":"NUNAVUT","mode":"s"}],"type":"land","quizRegion":"North Americas","quizSubRegion":"","region":"Americas","intermediateRegion":"","subRegion":"Northern America","capital":{"name":"Iqaluit","aliases":[{"val":"IQALUIT","mode":"s"}],"speech":null,"lat":63.749444,"lon":-68.521667,"timezone":"America/Iqaluit","state":"NU","ipa":""},"lat":67.35,"lon":-90.9,"dotX":0,"dotY":0,"additionalCities":[],"ipa":"","nativeName":"","areaSqKm":2093190,"areaSqMi":808190},{"iso2":"NS","iso3":"NS","name":"Nova Scotia","letter":"N","audio":"NOVASCOTIA.mp3","aliases":[{"val":"NOVASCOTIA","mode":"s"}],"type":"land","quizRegion":"North Americas","quizSubRegion":"","region":"Americas","intermediateRegion":"","subRegion":"Northern America","capital":{"name":"Halifax","aliases":[{"val":"HALIFAX","mode":"s"}],"speech":null,"lat":44.64,"lon":-63.59,"timezone":"America/Halifax","state":"NS","ipa":""},"lat":45,"lon":-63,"dotX":0,"dotY":0,"additionalCities":[],"ipa":"","nativeName":"","areaSqKm":55284,"areaSqMi":21345},{"iso2":"NT","iso3":"NT","name":"Northwest Territories","letter":"N","audio":"NORTHWESTTERRITORIES.mp3","aliases":[{"val":"NORTHWESTTERRITORIES","mode":"s"}],"type":"land","quizRegion":"North Americas","quizSubRegion":"","region":"Americas","intermediateRegion":"","subRegion":"Northern America","capital":{"name":"Yellowknife","aliases":[{"val":"YELLOWKNIFE","mode":"s"}],"speech":null,"lat":62.453611,"lon":-114.37,"timezone":"America/Yellowknife","state":"NT","ipa":""},"lat":67,"lon":-121,"dotX":0,"dotY":0,"additionalCities":[],"ipa":"","nativeName":"","areaSqKm":1346106,"areaSqMi":519734},{"iso2":"NL","iso3":"NL","name":"Newfoundland and Labrador","letter":"N","audio":"NEWFOUNDLANDANDLABRADOR.mp3","aliases":[{"val":"NEWFOUNDLAND","mode":"s"}],"type":"land","quizRegion":"North Americas","quizSubRegion":"","region":"Americas","intermediateRegion":"","subRegion":"Northern America","capital":{"name":"St. John's","aliases":[{"val":"(ST|SAINT)JOHNS","mode":"r"}],"speech":null,"lat":47.567,"lon":-52.73,"timezone":"America/St_Johns","state":"NL","ipa":""},"lat":53.23,"lon":-59.999167,"dotX":0,"dotY":0,"additionalCities":[],"ipa":"","nativeName":"","areaSqKm":405212,"areaSqMi":156453},{"iso2":"NB","iso3":"NB","name":"New Brunswick","letter":"N","audio":"NEWBRUNSWICK.mp3","aliases":[{"val":"NEWBRUNSWICK","mode":"s"}],"type":"land","quizRegion":"North Americas","quizSubRegion":"","region":"Americas","intermediateRegion":"","subRegion":"Northern America","capital":{"name":"Fredericton","aliases":[{"val":"FREDERICTON","mode":"r"}],"speech":null,"lat":45.945278,"lon":-66.666667,"timezone":"America/Moncton","state":"NB","ipa":""},"lat":46.5,"lon":-66,"dotX":0,"dotY":0,"additionalCities":[],"ipa":"","nativeName":"","areaSqKm":72908,"areaSqMi":28150},{"iso2":"MB","iso3":"MB","name":"Manitoba","letter":"M","audio":"MANITOBA.mp3","aliases":[{"val":"MANITOBA","mode":"s"}],"type":"land","quizRegion":"North Americas","quizSubRegion":"","region":"Americas","intermediateRegion":"","subRegion":"Northern America","capital":{"name":"Winnipeg","aliases":[{"val":"WINNIPEG","mode":"r"}],"speech":null,"lat":49.89,"lon":-97.151,"timezone":"America/Winnipeg","state":"MB","ipa":""},"lat":55,"lon":-97,"dotX":0,"dotY":0,"additionalCities":[],"ipa":"","nativeName":"","areaSqKm":647797,"areaSqMi":250116},{"iso2":"BC","iso3":"BC","name":"British Columbia","letter":"B","audio":"BRITISHCOLUMBIA.mp3","aliases":[{"val":"BRITISHCOLUMBIA","mode":"s"}],"type":"land","quizRegion":"North Americas","quizSubRegion":"","region":"Americas","intermediateRegion":"","subRegion":"Northern America","capital":{"name":"Victoria","aliases":[{"val":"VICTORIA","mode":"r"}],"speech":null,"lat":48.428333,"lon":-123.364722,"timezone":"America/Vancouver","state":"BC","ipa":""},"lat":54,"lon":-125,"dotX":0,"dotY":0,"additionalCities":[],"ipa":"","nativeName":"","areaSqKm":944735,"areaSqMi":364764},{"iso2":"AB","iso3":"AB","name":"Alberta","letter":"B","audio":"ALBERTA.mp3","aliases":[{"val":"ALBERTA","mode":"s"}],"type":"land","quizRegion":"North Americas","quizSubRegion":"","region":"Americas","intermediateRegion":"","subRegion":"Northern America","capital":{"name":"Edmonton","aliases":[{"val":"EDMONTON","mode":"r"}],"speech":null,"lat":53.54,"lon":-113.53,"timezone":"America/Edmonton","state":"AB","ipa":""},"lat":54.5,"lon":-115,"dotX":0,"dotY":0,"additionalCities":[],"ipa":"","nativeName":"","areaSqKm":661849,"areaSqMi":255541},{"iso2":"PM","iso3":"SPM","name":"Saint Pierre and Miquelon","type":"island","quizRegion":"North Americas","quizSubRegion":"","region":"Americas","intermediateRegion":"","subRegion":"Northern America","capital":null,"letter":"S","audio":"SAINTPIERREANDMIQUELON.MP3","aliases":[{"val":"(ST|SAINT)PIERRE","mode":"r"}],"dotX":927.985,"dotY":294.985,"additionalCities":[],"areaSqKm":242,"areaSqMi":93,"ipa":"seɪnt piˈɛər ænd ˈmɪkəlɒn","nativeName":"Saint-Pierre et Miquelon"}]}